CONTRIBUTING.rst
HISTORY.rst
LICENSE
MANIFEST.in
README.rst
setup.cfg
setup.py
docs/Makefile
docs/background.rst
docs/conf.py
docs/contributing.rst
docs/development.rst
docs/history.rst
docs/index.rst
docs/installation.rst
docs/modules.rst
docs/pyoadr_ven.rst
docs/usage.rst
pyOADR_VEN.egg-info/PKG-INFO
pyOADR_VEN.egg-info/SOURCES.txt
pyOADR_VEN.egg-info/dependency_links.txt
pyOADR_VEN.egg-info/not-zip-safe
pyOADR_VEN.egg-info/requires.txt
pyOADR_VEN.egg-info/top_level.txt
pyoadr_ven/__init__.py
pyoadr_ven/agent.py
pyoadr_ven/builders.py
pyoadr_ven/database.py
pyoadr_ven/enums.py
pyoadr_ven/exceptions.py
pyoadr_ven/extractors.py
pyoadr_ven/models.py
pyoadr_ven/oadr_20b.py
pyoadr_ven/pyoadr_ven.py
pyoadr_ven/response_codes.py
pyoadr_ven/utils.py
pyoadr_ven/validation_schemas.py
tests/__init__.py
tests/conftest.py
tests/dev_setup.py
tests/factories.py
tests/test_events.py
tests/test_report_responses.py
tests/test_reports.py
tests/test_responses.py
tests/test_telemetry.py
tests/xml/crypto_experiment.xml
tests/xml/epri_vtn_distribute_event.xml
tests/xml/epri_vtn_response_not_registered.xml
tests/xml/epri_vtn_response_valid.xml
tests/xml/kisensum_vtn_cancel_event.xml
tests/xml/kisensum_vtn_registered_report.xml
tests/xml/sample_ven_poll_signed.xml
tests/xml/test_vtn_cancel_event.xml
tests/xml/test_vtn_distribute_event.xml
tests/xml/test_vtn_distribute_event_no_end.xml
tests/xml/test_vtn_distribute_event_variable.xml
tests/xml/test_vtn_registered_report.xml
tests/xml/ven_created_event.xml
tests/xml/ven_created_report.xml
tests/xml/ven_oadrRegisterReport.xml
tests/xml/ven_poll.xml
tests/xml/ven_register_report.xml
tests/xml/ven_update_report.xml
tests/xml/vtn_distribute_event.xml
tests/xml/vtn_empty_poll_response.xml
tests/xml/vtn_oadrRegisterReport_response.xml