Metadata-Version: 2.1
Name: pyOADR-VEN
Version: 0.6.0
Summary: OpenADR Virtual End Node
Home-page: https://carboncoop.gitlab.io/pyoadr-ven/
Author: Carbon Coop
Author-email: sam@carbon.coop
License: Apache Software License 2.0
Keywords: pyoadr_ven
Classifier: Development Status :: 2 - Pre-Alpha
Classifier: Intended Audience :: Developers
Classifier: License :: OSI Approved :: Apache Software License
Classifier: Natural Language :: English
Classifier: Programming Language :: Python :: 3.11
License-File: LICENSE
Requires-Dist: isodate
Requires-Dist: lxml
Requires-Dist: requests
Requires-Dist: signxml
Requires-Dist: pytz
Requires-Dist: python-dateutil
Requires-Dist: pony
Requires-Dist: pem
Requires-Dist: voluptuous
Requires-Dist: bs4
